setup.py
pagoda/__init__.py
pagoda/base.py
pagoda/cooper.py
pagoda/parser.py
pagoda/phasespace.py
pagoda/physics.py
pagoda/skeleton.py
pagoda/viewer.py
pagoda.egg-info/PKG-INFO
pagoda.egg-info/SOURCES.txt
pagoda.egg-info/dependency_links.txt
pagoda.egg-info/requires.txt
pagoda.egg-info/top_level.txt