Metadata-Version: 1.1
Name: pagoda
Version: 0.0.2
Summary: yet another OpenGL-with-physics simulation framework
Home-page: http://github.com/EmbodiedCognition/py-sim/
Author: Leif Johnson
Author-email: leif@cs.utexas.edu
License: MIT
Keywords: simulation physics ode visualization
Platform: UNKNOWN
Classifier: Development Status :: 3 - Alpha
Classifier: Intended Audience :: Science/Research
Classifier: License :: OSI Approved :: MIT License
Classifier: Operating System :: OS Independent
Classifier: Topic :: Scientific/Engineering
Classifier: Topic :: Scientific/Engineering :: Artificial Intelligence
Classifier: Topic :: Scientific/Engineering :: Physics
Classifier: Topic :: Scientific/Engineering :: Visualization
